Metadata-Version: 2.4
Name: iflow-mcp-bilibili-mcp-server
Version: 0.1.0
Summary: Add your description here
Requires-Python: >=3.12
License-File: LICENSE
Requires-Dist: bilibili-api-python>=17.1.4
Requires-Dist: mcp[cli]>=1.4.1
Requires-Dist: requests>=2.32.3
Dynamic: license-file
